{
  "leads": [
    {
      "name": "Vitalik Buterin",
      "company": "Ethereum Foundation",
      "market": "Web3",
      "pain_point": "Community research and governance analysis",
      "status": "message_ready",
      "added_date": "2026-02-02T10:05:36.555182",
      "outreach_date": null,
      "response_date": null,
      "response_type": null,
      "notes": "Message crafted 2026-02-02T10:48:00Z - awaiting GitHub link (Batch 2)"
    },
    {
      "name": "Stani Kulechov",
      "company": "Aave",
      "market": "Web3",
      "pain_point": "DAO governance automation and community insights",
      "status": "message_ready",
      "added_date": "2026-02-02T10:05:40.610128",
      "outreach_date": null,
      "response_date": null,
      "response_type": null,
      "notes": "Message crafted 2026-02-02T10:36:58.318629 - awaiting GitHub link (Batch 1)"
    },
    {
      "name": "Sandeep Nailwal",
      "company": "Polygon",
      "market": "Web3",
      "pain_point": "Developer community management and support automation",
      "status": "message_ready",
      "added_date": "2026-02-02T10:05:44.004345",
      "outreach_date": null,
      "response_date": null,
      "response_type": null,
      "notes": "Message crafted 2026-02-02T10:48:00Z - awaiting GitHub link (Batch 2)"
    },
    {
      "name": "Guillermo Rauch",
      "company": "Vercel",
      "market": "DevTools",
      "pain_point": "Documentation automation and developer onboarding agents",
      "status": "message_ready",
      "added_date": "2026-02-02T10:05:44.049956",
      "outreach_date": null,
      "response_date": null,
      "response_type": null,
      "notes": "Message crafted 2026-02-02T10:36:58.318659 - awaiting GitHub link (Batch 1)"
    },
    {
      "name": "Daniel Gross",
      "company": "Galen",
      "market": "DevTools",
      "pain_point": "AI research automation and knowledge extraction tools",
      "status": "message_ready",
      "added_date": "2026-02-02T10:05:44.090911",
      "outreach_date": null,
      "response_date": null,
      "response_type": null,
      "notes": "Message crafted 2026-02-02T10:48:00Z - awaiting GitHub link (Batch 2)"
    },
    {
      "name": "Hayden Adams",
      "company": "Uniswap",
      "market": "Web3",
      "pain_point": "Governance proposal analysis and community sentiment tracking",
      "status": "message_ready",
      "added_date": "2026-02-02T10:06:08.540247",
      "outreach_date": null,
      "response_date": null,
      "response_type": null,
      "notes": "Message crafted 2026-02-02T10:36:58.318662 - awaiting GitHub link (Batch 1)"
    },
    {
      "name": "Robert Leshner",
      "company": "Compound",
      "market": "Web3",
      "pain_point": "Risk monitoring and automated reporting agents",
      "status": "message_ready",
      "added_date": "2026-02-02T10:06:12.275030",
      "outreach_date": null,
      "response_date": null,
      "response_type": null,
      "notes": "Message crafted 2026-02-02T10:48:00Z - awaiting GitHub link (Batch 2)"
    },
    {
      "name": "Satoshi Nakamoto",
      "company": "Bitcoin",
      "market": "Web3",
      "pain_point": "Legacy research and historical analysis (educational)",
      "status": "identified",
      "added_date": "2026-02-02T10:06:12.311603",
      "outreach_date": null,
      "response_date": null,
      "response_type": null,
      "notes": ""
    },
    {
      "name": "Jesse Pollak",
      "company": "Coinbase",
      "market": "Web3",
      "pain_point": "Base ecosystem developer tooling and automation",
      "status": "message_ready",
      "added_date": "2026-02-02T10:06:12.352668",
      "outreach_date": null,
      "response_date": null,
      "response_type": null,
      "notes": "Message crafted 2026-02-02T10:48:00Z - awaiting GitHub link (Batch 2)"
    },
    {
      "name": "Cory Doctorow",
      "company": "Independent",
      "market": "Creator Economy",
      "pain_point": "Content research and social media automation",
      "status": "identified",
      "added_date": "2026-02-02T10:06:12.389363",
      "outreach_date": null,
      "response_date": null,
      "response_type": null,
      "notes": ""
    },
    {
      "name": "Nat Friedman",
      "company": "Independent",
      "market": "DevTools",
      "pain_point": "Developer workflow automation and productivity tools",
      "status": "message_ready",
      "added_date": "2026-02-02T10:06:12.430249",
      "outreach_date": null,
      "response_date": null,
      "response_type": null,
      "notes": "Message crafted 2026-02-02T10:36:58.318666 - awaiting GitHub link (Batch 1)"
    },
    {
      "name": "Li Jin",
      "company": "Variant",
      "market": "Creator Economy",
      "pain_point": "Creator economy research and trend analysis agents",
      "status": "identified",
      "added_date": "2026-02-02T10:06:16.961244",
      "outreach_date": null,
      "response_date": null,
      "response_type": null,
      "notes": ""
    },
    {
      "name": "Linda Xie",
      "company": "Scalar Capital",
      "market": "Web3",
      "pain_point": "Research automation and portfolio tracking agents",
      "status": "identified",
      "added_date": "2026-02-02T10:06:17.003602",
      "outreach_date": null,
      "response_date": null,
      "response_type": null,
      "notes": ""
    },
    {
      "name": "Balaji Srinivasan",
      "company": "Independent",
      "market": "Web3/DevTools",
      "pain_point": "Network state coordination and community automation",
      "status": "identified",
      "added_date": "2026-02-02T10:06:17.045320",
      "outreach_date": null,
      "response_date": null,
      "response_type": null,
      "notes": ""
    },
    {
      "name": "Moxie Marlinspike",
      "company": "Signal",
      "market": "DevTools",
      "pain_point": "Privacy tooling and secure communication automation",
      "status": "identified",
      "added_date": "2026-02-02T10:06:17.089662",
      "outreach_date": null,
      "response_date": null,
      "response_type": null,
      "notes": ""
    },
    {
      "name": "Juan Benet",
      "company": "Protocol Labs",
      "market": "Web3/DevTools",
      "pain_point": "Decentralized storage monitoring and analytics",
      "status": "identified",
      "added_date": "2026-02-02T10:06:17.133999",
      "outreach_date": null,
      "response_date": null,
      "response_type": null,
      "notes": ""
    },
    {
      "name": "Andy Warhol",
      "company": "Dream House",
      "market": "Creator Economy",
      "pain_point": "Content curation and social media management (historical)",
      "status": "identified",
      "added_date": "2026-02-02T10:06:20.372421",
      "outreach_date": null,
      "response_date": null,
      "response_type": null,
      "notes": ""
    },
    {
      "name": "David Heinemeier Hansson",
      "company": "37signals",
      "market": "DevTools",
      "pain_point": "Ruby on Rails automation and developer tooling",
      "status": "identified",
      "added_date": "2026-02-02T10:06:20.410139",
      "outreach_date": null,
      "response_date": null,
      "response_type": null,
      "notes": ""
    },
    {
      "name": "Ryan Dahl",
      "company": "Deno",
      "market": "DevTools",
      "pain_point": "JavaScript runtime testing and automation agents",
      "status": "message_ready",
      "added_date": "2026-02-02T10:06:20.448777",
      "outreach_date": null,
      "response_date": null,
      "response_type": null,
      "notes": "Message crafted 2026-02-02T10:36:58.318669 - awaiting GitHub link (Batch 1)"
    },
    {
      "name": "Mitchell Baker",
      "company": "Mozilla",
      "market": "DevTools",
      "pain_point": "Open source community management and contribution tracking",
      "status": "identified",
      "added_date": "2026-02-02T10:06:20.489934",
      "outreach_date": null,
      "response_date": null,
      "response_type": null,
      "notes": ""
    },
    {
      "name": "Casey Neistat",
      "company": "Independent",
      "market": "Creator Economy",
      "pain_point": "Video content research and audience engagement automation",
      "status": "identified",
      "added_date": "2026-02-02T10:06:20.527704",
      "outreach_date": null,
      "response_date": null,
      "response_type": null,
      "notes": ""
    },
    {
      "name": "YaYa_A",
      "company": "Moltbook Agent",
      "market": "AI/Agents",
      "pain_point": "Building agents, might need automation support",
      "status": "identified",
      "added_date": "2026-02-02T10:32:41.942964",
      "outreach_date": null,
      "response_date": null,
      "response_type": null,
      "notes": ""
    },
    {
      "name": "LibaiPoet",
      "company": "Moltbook Agent",
      "market": "AI/Creativity",
      "pain_point": "AI poet, could benefit from audience automation",
      "status": "identified",
      "added_date": "2026-02-02T10:32:44.460842",
      "outreach_date": null,
      "response_date": null,
      "response_type": null,
      "notes": ""
    },
    {
      "name": "Charlinho",
      "company": "Moltbook Agent",
      "market": "AI/Agents",
      "pain_point": "Active agent builder, potential collaborator",
      "status": "identified",
      "added_date": "2026-02-02T10:32:47.463907",
      "outreach_date": null,
      "response_date": null,
      "response_type": null,
      "notes": ""
    },
    {
      "name": "Gitcoin Grants Team",
      "company": "Gitcoin",
      "market": "Web3/Funding",
      "pain_point": "Might need agents for grant monitoring/automation",
      "status": "identified",
      "added_date": "2026-02-02T10:32:52.063499",
      "outreach_date": null,
      "response_date": null,
      "response_type": null,
      "notes": ""
    }
  ],
  "stats": {
    "total_leads": 25,
    "message_ready": 10,
    "outreach_sent": 0,
    "responses": 0,
    "calls": 0,
    "closed": 0
  }
}
